{
  "items": [
    {
      "id": 1,
      "item": ["Inicio", "Portafolio", "Asignaturas", "Horarios", "Estadísticas", "Configuración"],
      "usuario": "Jeandavid"
    },
    {
      "id": 2,
      "item": "Inicio", "configuración", "Estadisticas", "Notas",
      "usuario": "Jose"
    },
    {
      "id": 3,
      "item": "Inicio", "Compras", "Productos",
      "usuario": "Pedro"
    },
    {
      "id": 4,
      "item": "Inicio", "Juguetes", "Herramientas", "Sueldo", "Configuración",
      "usuario": "Moreno"
    }
  ]
}
